web3_rush-0.1.2.dist-info/METADATA
web3_rush-0.1.2.dist-info/WHEEL
web3_rush/__init__.py
web3_rush/web3_rush.pyi
web3_rush/py.typed
web3_rush/web3_rush.cpython-311-x86_64-linux-gnu.so
web3_rush-0.1.2.dist-info/RECORD
