Metadata-Version: 2.1
Name: web3-rush
Version: 0.1.2
